README.md
setup.py
symbionic/__init__.py
symbionic/_dataLoader.py
symbionic/_dataReceiver.py
symbionic/_plotting.py
symbionic.egg-info/PKG-INFO
symbionic.egg-info/SOURCES.txt
symbionic.egg-info/dependency_links.txt
symbionic.egg-info/not-zip-safe
symbionic.egg-info/requires.txt
symbionic.egg-info/top_level.txt
symbionic/tests/__init__.py
symbionic/tests/test_data_loader.py
symbionic/tests/test_data_receiver.py