Metadata-Version: 1.1
Name: symbionic
Version: 0.22
Summary: Code base for the Symbionic project
Home-page: https://github.com/matthijscox/symbionic
Author: Matthijs Cox
Author-email: matthijs.cox@gmail.com
License: GNU General Public License v3 (GPLv3)
Platform: UNKNOWN
Classifier: Development Status :: 3 - Alpha
Classifier: Topic :: Utilities
Classifier: License :: OSI Approved :: GNU General Public License v3 (GPLv3)
Classifier: Programming Language :: Python :: 3.6
